test_gleichgewicht.py
gleichgewicht/Zerlegen_einer_Kraft.py
gleichgewicht/__init__.py
gleichgewicht/actions.py
gleichgewicht/reactions.py
gleichgewicht/structure.py
gleichgewicht-0.0.1.dist-info/LICENSE
gleichgewicht-0.0.1.dist-info/METADATA
gleichgewicht-0.0.1.dist-info/WHEEL
gleichgewicht-0.0.1.dist-info/top_level.txt
gleichgewicht-0.0.1.dist-info/RECORD
