Metadata-Version: 2.1
Name: gleichgewicht
Version: 0.0.1
Summary: The gleichgewicht Package is designed for students at the Hochschule Luzern Technik and Architektur, with a specific focus on structural engineering. This package provides a comprehensive set of tools for analyzing structures and understanding the principles of gleichgewicht.
Author-email: Pascal Gitz <pascal.gitz@hslu.ch>
Project-URL: Homepage, https://github.com/PascalGitz/gleichgewicht
Project-URL: Bug Tracker, https://github.com/PascalGitz/gleichgewicht/issues
Classifier: Programming Language :: Python :: 3
Classifier: License :: OSI Approved :: GNU General Public License (GPL)
Classifier: Operating System :: Microsoft :: Windows
Requires-Python: >=3.10.12
License-File: LICENSE
Requires-Dist: numpy >=1.26.0
Requires-Dist: sympy >=1.12
Requires-Dist: matplotlib >=3.7.2
